Workbook

Sheet County Plans
A1: GridAid county plans: 5 urban and 5 rural counties
A2: Blue = data or site-picker results. Black = formulas. Green = linked from another sheet. Budgets update when you change the Assumptions sheet.
A4: County | B4: State | C4: FIPS | D4: Type | E4: Population (2020) | F4: Land area (sq mi) | G4: People per sq mi | H4: Medicare members | I4: Rely on powered equipment | J4: Share of Medicare members | K4: Home oxygen service | L4: Dialysis at a center | M4: Home health | N4: Hospice at home | O4: Reach (mi) | P4: Expected at sites | Q4: Power needed, low (kW) | R4: Power needed, high (kW) | S4: Sites from map (rural) | T4: Sites for full map coverage (rural) | U4: Recommended sites | V4: Sites, high estimate | W4: Budget, low ($) | X4: Budget, high ($) | Y4: FEMA share, low ($) | Z4: Local share, low ($) | AA4: Local share, high ($) | AB4: Budget per resident, low ($) | AC4: People in ZIP data (rural) | AD4: People reached, recommended sites (rural) | AE4: Coverage, recommended sites | AF4: How sites were counted | AG4: Fast start | AH4: Full setup
A5: Los Angeles County | B5: CA | C5: 06037 | D5: Urban | E5: 10014009 | F5: 4058 | G5: =E5/F5 -> 2467.7203 | H5: 1716142 | I5: 67311 | J5: =I5/H5 -> 0.039222279 | K5: 13254 | L5: 13765 | M5: 16517 | N5: 2735 | O5: =IF(D5="Rural",Assumptions!$B$11,Assumptions!$B$12) -> 3 | P5: =I5*Assumptions!$B$7 -> 16827.75 | Q5: =P5*Assumptions!$B$8/1000 -> 4627.6313 | R5: =P5*Assumptions!$B$9/1000 -> 9255.2625 | U5: =IF(D5="Rural",MAX(S5,ROUNDUP(R5/Assumptions!$B$10,0)),ROUNDUP(Q5/Assumptions!$B$10,0)) -> 47 | V5: =IF(D5="Rural",MAX(T5,ROUNDUP(R5/Assumptions!$B$10,0)),ROUNDUP(R5/Assumptions!$B$10,0)) -> 93 | W5: =U5*Assumptions!$B$5 -> 2741651 | X5: =V5*Assumptions!$B$5 -> 5424969 | Y5: =W5*Assumptions!$B$6 -> 2056238.2 | Z5: =W5-Y5 -> 685412.75 | AA5: =X5*(1-Assumptions!$B$6) -> 1356242.2 | AB5: =W5/E5 -> 0.27378156 | AE5: =IF(D5="Rural",AD5/AC5,"Not computed") -> Not computed | AF5: Power needs: expected people x watts / power per site | AG5: ="Hookups: weeks per site" -> Hookups: weeks per site | AH5: =IF(D5="Rural","Generators: months; grants can take years","Phase in by region over several years") -> Phase in by region over several years
A6: Cook County | B6: IL | C6: 17031 | D6: Urban | E6: 5275541 | F6: 945 | G6: =E6/F6 -> 5582.5831 | H6: 880036 | I6: 33574 | J6: =I6/H6 -> 0.038150712 | K6: 5550 | L6: 6193 | M6: 5852 | N6: 1386 | O6: =IF(D6="Rural",Assumptions!$B$11,Assumptions!$B$12) -> 3 | P6: =I6*Assumptions!$B$7 -> 8393.5 | Q6: =P6*Assumptions!$B$8/1000 -> 2308.2125 | R6: =P6*Assumptions!$B$9/1000 -> 4616.425 | U6: =IF(D6="Rural",MAX(S6,ROUNDUP(R6/Assumptions!$B$10,0)),ROUNDUP(Q6/Assumptions!$B$10,0)) -> 24 | V6: =IF(D6="Rural",MAX(T6,ROUNDUP(R6/Assumptions!$B$10,0)),ROUNDUP(R6/Assumptions!$B$10,0)) -> 47 | W6: =U6*Assumptions!$B$5 -> 1399992 | X6: =V6*Assumptions!$B$5 -> 2741651 | Y6: =W6*Assumptions!$B$6 -> 1049994 | Z6: =W6-Y6 -> 349998 | AA6: =X6*(1-Assumptions!$B$6) -> 685412.75 | AB6: =W6/E6 -> 0.26537411 | AE6: =IF(D6="Rural",AD6/AC6,"Not computed") -> Not computed | AF6: Power needs: expected people x watts / power per site | AG6: ="Hookups: weeks per site" -> Hookups: weeks per site | AH6: =IF(D6="Rural","Generators: months; grants can take years","Phase in by region over several years") -> Phase in by region over several years
A7: Harris County | B7: TX | C7: 48201 | D7: Urban | E7: 4731145 | F7: 1707.288 | G7: =E7/F7 -> 2771.1464 | H7: 672080 | I7: 28811 | J7: =I7/H7 -> 0.042868409 | K7: 4366 | L7: 6987 | M7: 5164 | N7: 1335 | O7: =IF(D7="Rural",Assumptions!$B$11,Assumptions!$B$12) -> 3 | P7: =I7*Assumptions!$B$7 -> 7202.75 | Q7: =P7*Assumptions!$B$8/1000 -> 1980.7562 | R7: =P7*Assumptions!$B$9/1000 -> 3961.5125 | U7: =IF(D7="Rural",MAX(S7,ROUNDUP(R7/Assumptions!$B$10,0)),ROUNDUP(Q7/Assumptions!$B$10,0)) -> 20 | V7: =IF(D7="Rural",MAX(T7,ROUNDUP(R7/Assumptions!$B$10,0)),ROUNDUP(R7/Assumptions!$B$10,0)) -> 40 | W7: =U7*Assumptions!$B$5 -> 1166660 | X7: =V7*Assumptions!$B$5 -> 2333320 | Y7: =W7*Assumptions!$B$6 -> 874995 | Z7: =W7-Y7 -> 291665 | AA7: =X7*(1-Assumptions!$B$6) -> 583330 | AB7: =W7/E7 -> 0.24659147 | AE7: =IF(D7="Rural",AD7/AC7,"Not computed") -> Not computed | AF7: Power needs: expected people x watts / power per site | AG7: ="Hookups: weeks per site" -> Hookups: weeks per site | AH7: =IF(D7="Rural","Generators: months; grants can take years","Phase in by region over several years") -> Phase in by region over several years
A8: Maricopa County | B8: AZ | C8: 04013 | D8: Urban | E8: 4420568 | F8: 9200 | G8: =E8/F8 -> 480.49652 | H8: 817022 | I8: 32883 | J8: =I8/H8 -> 0.040247386 | K8: 6677 | L8: 3712 | M8: 2797 | N8: 1279 | O8: =IF(D8="Rural",Assumptions!$B$11,Assumptions!$B$12) -> 3 | P8: =I8*Assumptions!$B$7 -> 8220.75 | Q8: =P8*Assumptions!$B$8/1000 -> 2260.7063 | R8: =P8*Assumptions!$B$9/1000 -> 4521.4125 | U8: =IF(D8="Rural",MAX(S8,ROUNDUP(R8/Assumptions!$B$10,0)),ROUNDUP(Q8/Assumptions!$B$10,0)) -> 23 | V8: =IF(D8="Rural",MAX(T8,ROUNDUP(R8/Assumptions!$B$10,0)),ROUNDUP(R8/Assumptions!$B$10,0)) -> 46 | W8: =U8*Assumptions!$B$5 -> 1341659 | X8: =V8*Assumptions!$B$5 -> 2683318 | Y8: =W8*Assumptions!$B$6 -> 1006244.2 | Z8: =W8-Y8 -> 335414.75 | AA8: =X8*(1-Assumptions!$B$6) -> 670829.5 | AB8: =W8/E8 -> 0.30350376 | AE8: =IF(D8="Rural",AD8/AC8,"Not computed") -> Not computed | AF8: Power needs: expected people x watts / power per site | AG8: ="Hookups: weeks per site" -> Hookups: weeks per site | AH8: =IF(D8="Rural","Generators: months; grants can take years","Phase in by region over several years") -> Phase in by region over several years
A9: Miami-Dade County | B9: FL | C9: 12086 | D9: Urban | E9: 2701767 | F9: 1898.753 | G9: =E9/F9 -> 1422.9165 | H9: 525034 | I9: 23346 | J9: =I9/H9 -> 0.044465692 | K9: 5732 | L9: 3127 | M9: 2673 | N9: 1081 | O9: =IF(D9="Rural",Assumptions!$B$11,Assumptions!$B$12) -> 3 | P9: =I9*Assumptions!$B$7 -> 5836.5 | Q9: =P9*Assumptions!$B$8/1000 -> 1605.0375 | R9: =P9*Assumptions!$B$9/1000 -> 3210.075 | U9: =IF(D9="Rural",MAX(S9,ROUNDUP(R9/Assumptions!$B$10,0)),ROUNDUP(Q9/Assumptions!$B$10,0)) -> 17 | V9: =IF(D9="Rural",MAX(T9,ROUNDUP(R9/Assumptions!$B$10,0)),ROUNDUP(R9/Assumptions!$B$10,0)) -> 33 | W9: =U9*Assumptions!$B$5 -> 991661 | X9: =V9*Assumptions!$B$5 -> 1924989 | Y9: =W9*Assumptions!$B$6 -> 743745.75 | Z9: =W9-Y9 -> 247915.25 | AA9: =X9*(1-Assumptions!$B$6) -> 481247.25 | AB9: =W9/E9 -> 0.36704164 | AE9: =IF(D9="Rural",AD9/AC9,"Not computed") -> Not computed | AF9: Power needs: expected people x watts / power per site | AG9: ="Hookups: weeks per site" -> Hookups: weeks per site | AH9: =IF(D9="Rural","Generators: months; grants can take years","Phase in by region over several years") -> Phase in by region over several years
A10: Athens County | B10: OH | C10: 39009 | D10: Rural | E10: 62431 | F10: 504 | G10: =E10/F10 -> 123.87103 | H10: 12713 | I10: 845 | J10: =I10/H10 -> 0.066467396 | K10: 284 | L10: 88 | M10: 148 | N10: 77 | O10: =IF(D10="Rural",Assumptions!$B$11,Assumptions!$B$12) -> 10 | P10: =I10*Assumptions!$B$7 -> 211.25 | Q10: =P10*Assumptions!$B$8/1000 -> 58.09375 | R10: =P10*Assumptions!$B$9/1000 -> 116.1875 | S10: 3 | T10: 4 | U10: =IF(D10="Rural",MAX(S10,ROUNDUP(R10/Assumptions!$B$10,0)),ROUNDUP(Q10/Assumptions!$B$10,0)) -> 3 | V10: =IF(D10="Rural",MAX(T10,ROUNDUP(R10/Assumptions!$B$10,0)),ROUNDUP(R10/Assumptions!$B$10,0)) -> 4 | W10: =U10*Assumptions!$B$5 -> 174999 | X10: =V10*Assumptions!$B$5 -> 233332 | Y10: =W10*Assumptions!$B$6 -> 131249.25 | Z10: =W10-Y10 -> 43749.75 | AA10: =X10*(1-Assumptions!$B$6) -> 58333 | AB10: =W10/E10 -> 2.8030786 | AC10: 829 | AD10: 805 | AE10: =IF(D10="Rural",AD10/AC10,"Not computed") -> 0.97104946 | AF10: Site picker on 7 real library branches, 10 mi. Full coverage adds a site near Amesville. | AG10: ="Hookups: weeks per site" -> Hookups: weeks per site | AH10: =IF(D10="Rural","Generators: months; grants can take years","Phase in by region over several years") -> Generators: months; grants can take years
A11: Harlan County | B11: KY | C11: 21095 | D11: Rural | E11: 26831 | F11: 466 | G11: =E11/F11 -> 57.577253 | H11: 6953 | I11: 875 | J11: =I11/H11 -> 0.12584496 | K11: 207 | L11: 88 | M11: 165 | N11: 55 | O11: =IF(D11="Rural",Assumptions!$B$11,Assumptions!$B$12) -> 10 | P11: =I11*Assumptions!$B$7 -> 218.75 | Q11: =P11*Assumptions!$B$8/1000 -> 60.15625 | R11: =P11*Assumptions!$B$9/1000 -> 120.3125 | S11: 2 | T11: 4 | U11: =IF(D11="Rural",MAX(S11,ROUNDUP(R11/Assumptions!$B$10,0)),ROUNDUP(Q11/Assumptions!$B$10,0)) -> 2 | V11: =IF(D11="Rural",MAX(T11,ROUNDUP(R11/Assumptions!$B$10,0)),ROUNDUP(R11/Assumptions!$B$10,0)) -> 4 | W11: =U11*Assumptions!$B$5 -> 116666 | X11: =V11*Assumptions!$B$5 -> 233332 | Y11: =W11*Assumptions!$B$6 -> 87499.5 | Z11: =W11-Y11 -> 29166.5 | AA11: =X11*(1-Assumptions!$B$6) -> 58333 | AB11: =W11/E11 -> 4.3481793 | AC11: 861 | AD11: 833 | AE11: =IF(D11="Rural",AD11/AC11,"Not computed") -> 0.96747967 | AF11: Site picker on ZIP code centers (town centers), 10 mi | AG11: ="Hookups: weeks per site" -> Hookups: weeks per site | AH11: =IF(D11="Rural","Generators: months; grants can take years","Phase in by region over several years") -> Generators: months; grants can take years
A12: Coos County | B12: NH | C12: 33007 | D12: Rural | E12: 31268 | F12: 1795 | G12: =E12/F12 -> 17.419499 | H12: 11023 | I12: 466 | J12: =I12/H12 -> 0.042275243 | K12: 157 | L12: 66 | M12: 110 | N12: 22 | O12: =IF(D12="Rural",Assumptions!$B$11,Assumptions!$B$12) -> 10 | P12: =I12*Assumptions!$B$7 -> 116.5 | Q12: =P12*Assumptions!$B$8/1000 -> 32.0375 | R12: =P12*Assumptions!$B$9/1000 -> 64.075 | S12: 5 | T12: 8 | U12: =IF(D12="Rural",MAX(S12,ROUNDUP(R12/Assumptions!$B$10,0)),ROUNDUP(Q12/Assumptions!$B$10,0)) -> 5 | V12: =IF(D12="Rural",MAX(T12,ROUNDUP(R12/Assumptions!$B$10,0)),ROUNDUP(R12/Assumptions!$B$10,0)) -> 8 | W12: =U12*Assumptions!$B$5 -> 291665 | X12: =V12*Assumptions!$B$5 -> 466664 | Y12: =W12*Assumptions!$B$6 -> 218748.75 | Z12: =W12-Y12 -> 72916.25 | AA12: =X12*(1-Assumptions!$B$6) -> 116666 | AB12: =W12/E12 -> 9.3279071 | AC12: 477 | AD12: 438 | AE12: =IF(D12="Rural",AD12/AC12,"Not computed") -> 0.91823899 | AF12: Site picker on ZIP code centers (town centers), 10 mi | AG12: ="Hookups: weeks per site" -> Hookups: weeks per site | AH12: =IF(D12="Rural","Generators: months; grants can take years","Phase in by region over several years") -> Generators: months; grants can take years
A13: Big Horn County | B13: MT | C13: 30003 | D13: Rural | E13: 13124 | F13: 4995 | G13: =E13/F13 -> 2.6274274 | H13: 2101 | I13: 223 | J13: =I13/H13 -> 0.10613993 | K13: 133 | L13: 73 | M13: 0 | N13: 0 | O13: =IF(D13="Rural",Assumptions!$B$11,Assumptions!$B$12) -> 10 | P13: =I13*Assumptions!$B$7 -> 55.75 | Q13: =P13*Assumptions!$B$8/1000 -> 15.33125 | R13: =P13*Assumptions!$B$9/1000 -> 30.6625 | S13: 8 | T13: 10 | U13: =IF(D13="Rural",MAX(S13,ROUNDUP(R13/Assumptions!$B$10,0)),ROUNDUP(Q13/Assumptions!$B$10,0)) -> 8 | V13: =IF(D13="Rural",MAX(T13,ROUNDUP(R13/Assumptions!$B$10,0)),ROUNDUP(R13/Assumptions!$B$10,0)) -> 10 | W13: =U13*Assumptions!$B$5 -> 466664 | X13: =V13*Assumptions!$B$5 -> 583330 | Y13: =W13*Assumptions!$B$6 -> 349998 | Z13: =W13-Y13 -> 116666 | AA13: =X13*(1-Assumptions!$B$6) -> 145832.5 | AB13: =W13/E13 -> 35.558062 | AC13: 223 | AD13: 201 | AE13: =IF(D13="Rural",AD13/AC13,"Not computed") -> 0.90134529 | AF13: Site picker on ZIP code centers (town centers), 10 mi | AG13: ="Hookups: weeks per site" -> Hookups: weeks per site | AH13: =IF(D13="Rural","Generators: months; grants can take years","Phase in by region over several years") -> Generators: months; grants can take years
A14: Sunflower County | B14: MS | C14: 28133 | D14: Rural | E14: 25971 | F14: 697.759 | G14: =E14/F14 -> 37.220588 | H14: 4842 | I14: 359 | J14: =I14/H14 -> 0.074142916 | K14: 92 | L14: 111 | M14: 83 | N14: 33 | O14: =IF(D14="Rural",Assumptions!$B$11,Assumptions!$B$12) -> 10 | P14: =I14*Assumptions!$B$7 -> 89.75 | Q14: =P14*Assumptions!$B$8/1000 -> 24.68125 | R14: =P14*Assumptions!$B$9/1000 -> 49.3625 | S14: 3 | T14: 4 | U14: =IF(D14="Rural",MAX(S14,ROUNDUP(R14/Assumptions!$B$10,0)),ROUNDUP(Q14/Assumptions!$B$10,0)) -> 3 | V14: =IF(D14="Rural",MAX(T14,ROUNDUP(R14/Assumptions!$B$10,0)),ROUNDUP(R14/Assumptions!$B$10,0)) -> 4 | W14: =U14*Assumptions!$B$5 -> 174999 | X14: =V14*Assumptions!$B$5 -> 233332 | Y14: =W14*Assumptions!$B$6 -> 131249.25 | Z14: =W14-Y14 -> 43749.75 | AA14: =X14*(1-Assumptions!$B$6) -> 58333 | AB14: =W14/E14 -> 6.7382465 | AC14: 359 | AD14: 345 | AE14: =IF(D14="Rural",AD14/AC14,"Not computed") -> 0.96100279 | AF14: Site picker on ZIP code centers (town centers), 10 mi | AG14: ="Hookups: weeks per site" -> Hookups: weeks per site | AH14: =IF(D14="Rural","Generators: months; grants can take years","Phase in by region over several years") -> Generators: months; grants can take years
A16: Urban total | E16: =SUMIFS(E5:E14,$D$5:$D$14,"Urban") -> 27143030 | I16: =SUMIFS(I5:I14,$D$5:$D$14,"Urban") -> 185925 | U16: =SUMIFS(U5:U14,$D$5:$D$14,"Urban") -> 131 | V16: =SUMIFS(V5:V14,$D$5:$D$14,"Urban") -> 259 | W16: =SUMIFS(W5:W14,$D$5:$D$14,"Urban") -> 7641623 | X16: =SUMIFS(X5:X14,$D$5:$D$14,"Urban") -> 15108247 | Y16: =SUMIFS(Y5:Y14,$D$5:$D$14,"Urban") -> 5731217.2 | Z16: =SUMIFS(Z5:Z14,$D$5:$D$14,"Urban") -> 1910405.8 | AA16: =SUMIFS(AA5:AA14,$D$5:$D$14,"Urban") -> 3777061.8
A17: Rural total | E17: =SUMIFS(E5:E14,$D$5:$D$14,"Rural") -> 159625 | I17: =SUMIFS(I5:I14,$D$5:$D$14,"Rural") -> 2768 | U17: =SUMIFS(U5:U14,$D$5:$D$14,"Rural") -> 21 | V17: =SUMIFS(V5:V14,$D$5:$D$14,"Rural") -> 30 | W17: =SUMIFS(W5:W14,$D$5:$D$14,"Rural") -> 1224993 | X17: =SUMIFS(X5:X14,$D$5:$D$14,"Rural") -> 1749990 | Y17: =SUMIFS(Y5:Y14,$D$5:$D$14,"Rural") -> 918744.75 | Z17: =SUMIFS(Z5:Z14,$D$5:$D$14,"Rural") -> 306248.25 | AA17: =SUMIFS(AA5:AA14,$D$5:$D$14,"Rural") -> 437497.5
A19: How to read this sheet
A20: Recommended sites: rural = the larger of (sites needed to reach at least 90% of people in the ZIP data, from the site picker) and (sites needed for power). Urban = sites needed for power at the low wattage.
A21: Sites, high estimate: rural = sites to reach everyone in the ZIP data. Urban = sites needed at the high wattage.
A22: Budget = sites x cost per site (Assumptions). FEMA share uses the 75% split from one state program; actual shares vary.
A23: People counts are Medicare members only (HHS emPOWER, county layer, updated August 2026). ZIP data hides counts of 1 to 10 as 11, so ZIP totals can differ from county totals.
A24: Urban coverage is not computed here: big counties have hundreds of ZIP codes and need the full app. Urban site counts are driven by power and room, not distance.
A25: Costs are planning estimates, not quotes. Regional price differences are not included.

Sheet Rural Site Plans
A1: Rural site plans from the site picker
A2: Each row adds the site that reaches the most people not yet covered (10 mile straight-line reach). Best possible = every combination checked, up to 6 sites.
A4: County | B4: Site # | C4: Site | D4: ZIP | E4: New people reached | F4: Total reached | G4: People in ZIP data | H4: Share reached | I4: Best possible with this many | J4: Site picker vs best
A5: Athens County, OH | B5: 1 | C5: Chauncey Public Library | D5: 45719 | E5: 597 | F5: 597 | G5: 829 | H5: =F5/G5 -> 0.72014475 | I5: 597 | J5: =F5/I5 -> 1
A6: Athens County, OH | B6: 2 | C6: Coolville Public Library | D6: 45723 | E6: 107 | F6: 704 | G6: 829 | H6: =F6/G6 -> 0.84921592 | I6: 704 | J6: =F6/I6 -> 1
A7: Athens County, OH | B7: 3 | C7: Wells (Albany) Public Library | D7: 45710 | E7: 101 | F7: 805 | G7: 829 | H7: =F7/G7 -> 0.97104946 | I7: 805 | J7: =F7/I7 -> 1
A8: Harlan County, KY | B8: 1 | C8: Public building near Coalgood | D8: 40818 | E8: 638 | F8: 638 | G8: 861 | H8: =F8/G8 -> 0.74099884 | I8: 638 | J8: =IF(ISNUMBER(I8),F8/I8,"") -> 1
A9: Harlan County, KY | B9: 2 | C9: Public building near Lynch | D9: 40855 | E9: 195 | F9: 833 | G9: 861 | H9: =F9/G9 -> 0.96747967 | I9: 833 | J9: =IF(ISNUMBER(I9),F9/I9,"") -> 1
A10: Harlan County, KY | B10: 3 | C10: Public building near Coldiron | D10: 40819 | E10: 17 | F10: 850 | G10: 861 | H10: =F10/G10 -> 0.98722416 | I10: 861 | J10: =IF(ISNUMBER(I10),F10/I10,"") -> 0.98722416
A11: Harlan County, KY | B11: 4 | C11: Public building near Big Laurel | D11: 40808 | E11: 11 | F11: 861 | G11: 861 | H11: =F11/G11 -> 1 | I11: 861 | J11: =IF(ISNUMBER(I11),F11/I11,"") -> 1
A12: Coos County, NH | B12: 1 | C12: Public building near Berlin | D12: 03570 | E12: 224 | F12: 224 | G12: 477 | H12: =F12/G12 -> 0.46960168 | I12: 224 | J12: =IF(ISNUMBER(I12),F12/I12,"") -> 1
A13: Coos County, NH | B13: 2 | C13: Public building near Lancaster | D13: 03584 | E13: 122 | F13: 346 | G13: 477 | H13: =F13/G13 -> 0.72536688 | I13: 346 | J13: =IF(ISNUMBER(I13),F13/I13,"") -> 1
A14: Coos County, NH | B14: 3 | C14: Public building near Colebrook | D14: 03576 | E14: 47 | F14: 393 | G14: 477 | H14: =F14/G14 -> 0.82389937 | I14: 393 | J14: =IF(ISNUMBER(I14),F14/I14,"") -> 1
A15: Coos County, NH | B15: 4 | C15: Public building near Twin Mountain | D15: 03595 | E15: 27 | F15: 420 | G15: 477 | H15: =F15/G15 -> 0.88050314 | I15: 437 | J15: =IF(ISNUMBER(I15),F15/I15,"") -> 0.9610984
A16: Coos County, NH | B16: 5 | C16: Public building near Pittsburg | D16: 03592 | E16: 18 | F16: 438 | G16: 477 | H16: =F16/G16 -> 0.91823899 | I16: 455 | J16: =IF(ISNUMBER(I16),F16/I16,"") -> 0.96263736
A17: Coos County, NH | B17: 6 | C17: Public building near Groveton | D17: 03582 | E17: 17 | F17: 455 | G17: 477 | H17: =F17/G17 -> 0.95387841 | I17: 466 | J17: =IF(ISNUMBER(I17),F17/I17,"") -> 0.97639485
A18: Coos County, NH | B18: 7 | C18: Public building near Errol | D18: 03579 | E18: 11 | F18: 466 | G18: 477 | H18: =F18/G18 -> 0.9769392 | I18: Not checked | J18: =IF(ISNUMBER(I18),F18/I18,"")
A19: Coos County, NH | B19: 8 | C19: Public building near Jackson | D19: 03846 | E19: 11 | F19: 477 | G19: 477 | H19: =F19/G19 -> 1 | I19: Not checked | J19: =IF(ISNUMBER(I19),F19/I19,"")
A20: Big Horn County, MT | B20: 1 | C20: Public building near Hardin | D20: 59034 | E20: 93 | F20: 93 | G20: 223 | H20: =F20/G20 -> 0.41704036 | I20: 93 | J20: =IF(ISNUMBER(I20),F20/I20,"") -> 1
A21: Big Horn County, MT | B21: 2 | C21: Public building near Crow Agency | D21: 59022 | E21: 32 | F21: 125 | G21: 223 | H21: =F21/G21 -> 0.56053812 | I21: 125 | J21: =IF(ISNUMBER(I21),F21/I21,"") -> 1
A22: Big Horn County, MT | B22: 3 | C22: Public building near Lodge Grass | D22: 59050 | E22: 20 | F22: 145 | G22: 223 | H22: =F22/G22 -> 0.65022422 | I22: 145 | J22: =IF(ISNUMBER(I22),F22/I22,"") -> 1
A23: Big Horn County, MT | B23: 4 | C23: Public building near Busby | D23: 59016 | E23: 12 | F23: 157 | G23: 223 | H23: =F23/G23 -> 0.70403587 | I23: 157 | J23: =IF(ISNUMBER(I23),F23/I23,"") -> 1
A24: Big Horn County, MT | B24: 5 | C24: Public building near Pryor | D24: 59066 | E24: 11 | F24: 168 | G24: 223 | H24: =F24/G24 -> 0.75336323 | I24: 168 | J24: =IF(ISNUMBER(I24),F24/I24,"") -> 1
A25: Big Horn County, MT | B25: 6 | C25: Public building near Garryowen | D25: 59031 | E25: 11 | F25: 179 | G25: 223 | H25: =F25/G25 -> 0.80269058 | I25: 179 | J25: =IF(ISNUMBER(I25),F25/I25,"") -> 1
A26: Big Horn County, MT | B26: 7 | C26: Public building near Fort Smith | D26: 59035 | E26: 11 | F26: 190 | G26: 223 | H26: =F26/G26 -> 0.85201794 | I26: Not checked | J26: =IF(ISNUMBER(I26),F26/I26,"")
A27: Big Horn County, MT | B27: 8 | C27: Public building near Saint Xavier | D27: 59075 | E27: 11 | F27: 201 | G27: 223 | H27: =F27/G27 -> 0.90134529 | I27: Not checked | J27: =IF(ISNUMBER(I27),F27/I27,"")
A28: Big Horn County, MT | B28: 9 | C28: Public building near Wyola | D28: 59089 | E28: 11 | F28: 212 | G28: 223 | H28: =F28/G28 -> 0.95067265 | I28: Not checked | J28: =IF(ISNUMBER(I28),F28/I28,"")
A29: Big Horn County, MT | B29: 10 | C29: Public building near Decker | D29: 59025 | E29: 11 | F29: 223 | G29: 223 | H29: =F29/G29 -> 1 | I29: Not checked | J29: =IF(ISNUMBER(I29),F29/I29,"")
A30: Sunflower County, MS | B30: 1 | C30: Public building near Sunflower | D30: 38778 | E30: 250 | F30: 250 | G30: 359 | H30: =F30/G30 -> 0.69637883 | I30: 250 | J30: =IF(ISNUMBER(I30),F30/I30,"") -> 1
A31: Sunflower County, MS | B31: 2 | C31: Public building near Doddsville | D31: 38736 | E31: 53 | F31: 303 | G31: 359 | H31: =F31/G31 -> 0.84401114 | I31: 303 | J31: =IF(ISNUMBER(I31),F31/I31,"") -> 1
A32: Sunflower County, MS | B32: 3 | C32: Public building near Drew | D32: 38737 | E32: 42 | F32: 345 | G32: 359 | H32: =F32/G32 -> 0.96100279 | I32: 345 | J32: =IF(ISNUMBER(I32),F32/I32,"") -> 1
A33: Sunflower County, MS | B33: 4 | C33: Public building near Inverness | D33: 38753 | E33: 14 | F33: 359 | G33: 359 | H33: =F33/G33 -> 1 | I33: 359 | J33: =IF(ISNUMBER(I33),F33/I33,"") -> 1
A35: Sites for Harlan, Coos, Big Horn and Sunflower are town centers (ZIP code centers), not specific buildings yet. Athens uses real library branches placed at their ZIP center.

Sheet Athens Libraries
A1: Athens County library branches (candidate sites)
A3: Branch | B3: Town | C3: ZIP | D3: Recommended | E3: Note
A4: Athens Public Library | B4: Athens | C4: 45701 | D4: No | E4: Reaches no one new after the top 3, but could share the load
A5: Chauncey Public Library | B5: Chauncey | C5: 45719 | D5: Yes, site 1 | E5: Reaches 597 people; check room for about 149 at once
A6: Coolville Public Library | B6: Coolville | C6: 45723 | D6: Yes, site 2 | E6: Adds 107 people
A7: Glouster Public Library | B7: Glouster | C7: 45732 | D7: No
A8: Nelsonville Public Library | B8: Nelsonville | C8: 45764 | D8: No
A9: The Plains Public Library | B9: The Plains | C9: 45780 | D9: No | E9: Could share the load with site 1
A10: Wells (Albany) Public Library | B10: Albany | C10: 45710 | D10: Yes, site 3 | E10: Adds 101 people
A12: Source: Athens County Public Libraries (myacpl.org). Not reached by any library within 10 miles: Amesville (ZIP 45711), 24 people.

Sheet Assumptions
A1: GridAid planning assumptions
A2: Blue cells are inputs. Yellow cells are placeholders the county should set. Every formula in the workbook uses these cells.
A4: Assumption | B4: Value | C4: Source or note
A5: Cost per site, permanent generator ($) | B5: 58333 | C5: NC Department of Public Safety, June 18, 2019: more than $1.4 million for 24 generators (22 to 500 kW) at public facilities. $1,400,000 / 24 = $58,333. 2019 dollars, an average, not a quote.
A6: FEMA share of cost | B6: 0.75 | C6: FEMA Hazard Mitigation Grant Program share in the same NC program (state paid 25%). Varies by program and state.
A7: Expected turnout at sites | B7: 0.25 | C7: PLACEHOLDER, not sourced. Share of people within reach who would come to a site during a long outage. The county should set this.
A8: Power per person, low (watts) | B8: 275 | C8: Inogen At Home oxygen concentrator at 5 liters per minute (Inogen energy calculator).
A9: Power per person, high (watts) | B9: 550 | C9: Derived: Inogen says many concentrators use more than twice 275 W.
A10: Power per site (kW) | B10: 100 | C10: PLANNING ASSUMPTION, not sourced. Sizes one generator at a typical small public building. NC program sizes ranged 22 to 500 kW.
A11: Reach, rural (miles) | B11: 10 | C11: Assumption. Straight-line distance used in the rural site picker.
A12: Reach, urban (miles) | B12: 3 | C12: Assumption. Shorter because people without a car can't travel far. Urban site counts use power needs, not distance.
A13: Diesel use, 100 kW generator at full load (gal/hr) | B13: 7.4 | C13: Herc Rentals: How to calculate diesel generator fuel consumption.
A14: Large whole-school generator, equipment only ($) | B14: 606291 | C14: WUFT, Feb 3, 2026: Suwannee County, FL, 1,000 kW generator plus transfer switches for an elementary school shelter. Labor and installation extra.
A15: Fuel per day, 100 kW at full load (gal) | B15: =B13*24 -> 177.6 | C15: Formula: gallons per hour x 24.

Sheet Outages
A1: Recent outage for each county
A3: County | B3: Date | C3: What happened | D3: Source
A4: Los Angeles County, CA | B4: Jan 8, 2025 | C4: Wildfires and Santa Ana winds: 40,573 SCE customers in the county under public safety power shutoffs; 123,335 more considered | D4: https://patch.com/california/los-angeles/140k-lose-electricity-public-safety-power-shutoffs-amid-fires
A5: Cook County, IL | B5: Jul 15, 2024 | C5: Tornado outbreak: more than 440,000 ComEd customers lost power; most restored by Jul 19 | D5: https://www.businesswire.com/news/home/20240717251696/en
A6: Harris County, TX | B6: Jul 8, 2024 | C6: Hurricane Beryl: more than 2.2 million CenterPoint customers lost power during a heat advisory; 1.1 million still out 3 days later | D6: https://www.axios.com/local/houston/2024/07/11/houston-power-outage-storm-beryl-centerpoint
A7: Maricopa County, AZ | B7: May 2023 study | C7: Georgia Tech study: a multiday blackout during a heat wave would send half of Phoenix residents to emergency care | D7: https://www.axios.com/local/phoenix/2023/05/24/heat-wave-black-out-phoenx-heat-deaths-hospital
A8: Miami-Dade County, FL | B8: Sep 11, 2017 | C8: Hurricane Irma: about 830,000 of 1.1 million without power, roughly three-quarters | D8: https://www.wgbh.org/news/2017-09-11/power-out-for-more-than-60-percent-of-florida-homes-and-businesses
A9: Athens County, OH | B9: Jun 29, 2012 | C9: Windstorm: about 87 to 91% of AEP customers without power; 90% restoration not expected until Jul 6 | D9: https://woub.org/?p=5527
A10: Harlan County, KY | B10: Late Sep 2024 | C10: Hurricane Helene: more than 6,000 people without power; local state of emergency | D10: https://www.wymt.com/2024/09/30/harlan-county-power-outage-update/
A11: Coos County, NH | B11: Oct 30, 2017 | C11: Windstorm: about 450,000 NH customers lost power statewide; North Country hardest hit for road damage. No Coos-only count found | D11: https://www.nhpr.org/nh-news/2017-10-30/update-n-h-sees-widespread-damage-from-severe-wind-rainstorm
A12: Big Horn County, MT | B12: Jun 11, 2022 | C12: Hardin downburst: winds estimated near 115 mph snapped power poles; about 1,778 customers lost power | D12: https://www.weather.gov/byz/June-11-2022-Hardin-Downburst
A13: Sunflower County, MS | B13: Jan 2026 | C13: Ice storm: more than 140,000 Mississippians without power; nearby Delta counties 92 to 96% out. No Sunflower-only figure found | D13: https://www.yahoo.com/news/articles/nearly-140-000-still-without-160954894.html

Sheet Sources
A1: Sources
A3: HHS emPOWER REST Service (county and ZIP layers, data updated Aug 17, 2026) | B3: https://services2.arcgis.com/ZQ4jTQn6k7VPXEwO/ArcGIS/rest/services/HHS_emPOWER_REST_Service_Public/FeatureServer
A4: 2020 Census population and land area: Wikipedia county infoboxes (U.S. Census Bureau figures) | B4: https://en.wikipedia.org/wiki/Athens_County,_Ohio (and matching pages for each county)
A5: NC Department of Public Safety: generators for critical public facilities (2019) | B5: https://ncdps.gov/news/press-releases/2019/06/18/communities-receive-generators-powering-critical-public
A6: WUFT: Suwannee County approves purchase of $600,000 generator (Feb 3, 2026) | B6: https://www.wuft.org/politics/2026-02-03/suwannee-county-approves-purchase-of-600-000-generator-for-emergency-shelter
A7: Inogen At Home energy calculator | B7: https://www.inogen.com/products/energy-savings-calculator/
A8: Herc Rentals: diesel generator fuel consumption | B8: https://blog.hercrentals.com/power-generation/how-to-calculate-diesel-generator-fuel-consumption/
A9: Athens County Public Libraries | B9: https://www.myacpl.org
